openweather_pws/__init__.py
openweather_pws/__main__.py
openweather_pws/openweather_pws.py
openweather_pws-1.0.2.dist-info/METADATA
openweather_pws-1.0.2.dist-info/WHEEL
openweather_pws-1.0.2.dist-info/top_level.txt
openweather_pws-1.0.2.dist-info/RECORD
