Metadata-Version: 2.1
Name: openweather-pws
Version: 1.0.2
Summary: Open Weather PWS API
Home-page: https://github.com/wwakabobik/openweather_pws
Author: Ilya Vereshchagin
Author-email: i.vereshchagin@gmail.com
License: UNKNOWN
Platform: UNKNOWN
Classifier: Programming Language :: Python :: 3
Classifier: License :: OSI Approved :: MIT License
Classifier: Operating System :: OS Independent
Requires-Python: >=3.7
Requires-Dist: requests
